FedModelKit/README.md
FedModelKit/__init__.py
FedModelKit/aggregator.py
FedModelKit/cli.py
FedModelKit/default_create_functions.py
FedModelKit/interface.py
FedModelKit/local_learner.py
FedModelKit/py.typed
FedModelKit/templates.py
FedModelKit/src/utils.py
FedModelKit/templates/__init__template.py
FedModelKit/templates/client_app_template.py
FedModelKit/templates/ds_template.ipynb
FedModelKit/templates/extern_pyproject_template.toml
FedModelKit/templates/main_template.py
FedModelKit/templates/pyproject_template.toml
FedModelKit/templates/readme_template.md
FedModelKit/templates/server_app_template.py
FedModelKit/templates/task_template.py
FedModelKit/templates/images/doSendModels.png
FedModelKit/templates/images/doWaitsForJobs.png
FedModelKit/templates/images/dsAggregateModels.png
FedModelKit/templates/images/dsDoneSubmittingJobs.png
FedModelKit/templates/images/dsSendsJobs.png
FedModelKit/templates/images/overview.png
fedmodelkit-0.6.8.dist-info/METADATA
fedmodelkit-0.6.8.dist-info/WHEEL
fedmodelkit-0.6.8.dist-info/entry_points.txt
fedmodelkit-0.6.8.dist-info/licenses/LICENSE
fedmodelkit-0.6.8.dist-info/RECORD
